blurthefaces/__init__.py
blurthefaces/blur.py
blurthefaces/detector.py
blurthefaces/utils.py
blurthefaces-0.1.5.dist-info/METADATA
blurthefaces-0.1.5.dist-info/WHEEL
blurthefaces-0.1.5.dist-info/top_level.txt
blurthefaces-0.1.5.dist-info/RECORD
